<?xml version="1.0"?>
<MovementPerformed>
  <GUID>DE4F72EB-0DF1-4D8B-AAD4-424AFC7AF855</GUID>
  <LiftedPosition xmlns:xsi="http://www.w3.org/2001/XMLSchema-instance" xsi:type="SpreaderPosition">
    <Gantry>1427.940000</Gantry>
    <Hoist>67.060000</Hoist>
    <Trolley>142.050000</Trolley>
    <SpreaderSize>40</SpreaderSize>
  </LiftedPosition>
  <DroppedPosition xmlns:xsi="http://www.w3.org/2001/XMLSchema-instance" xsi:type="SpreaderPosition">
    <Gantry>1427.930000</Gantry>
    <Hoist>124.390000</Hoist>
    <Trolley>-120.440000</Trolley>
    <SpreaderSize>40</SpreaderSize>
  </DroppedPosition>
</MovementPerformed>
