<?xml version="1.0"?>
<MovementPerformed>
  <GUID>11885CFE-1381-4792-AA5B-88BADA66B1F9</GUID>
  <LiftedPosition xmlns:xsi="http://www.w3.org/2001/XMLSchema-instance" xsi:type="SpreaderPosition">
    <Gantry>1857.400000</Gantry>
    <Hoist>65.160000</Hoist>
    <Trolley>63.350000</Trolley>
    <SpreaderSize>40</SpreaderSize>
  </LiftedPosition>
  <DroppedPosition xmlns:xsi="http://www.w3.org/2001/XMLSchema-instance" xsi:type="SpreaderPosition">
    <Gantry>1857.390000</Gantry>
    <Hoist>122.520000</Hoist>
    <Trolley>-119.770000</Trolley>
    <SpreaderSize>40</SpreaderSize>
  </DroppedPosition>
</MovementPerformed>
