<?xml version="1.0"?>
<MovementPerformed>
  <GUID>F938F517-E844-404A-B407-C85939F57042</GUID>
  <LiftedPosition xmlns:xsi="http://www.w3.org/2001/XMLSchema-instance" xsi:type="SpreaderPosition">
    <Gantry>2000.730000</Gantry>
    <Hoist>140.000000</Hoist>
    <Trolley>-71.840000</Trolley>
    <SpreaderSize>0</SpreaderSize>
  </LiftedPosition>
  <DroppedPosition xmlns:xsi="http://www.w3.org/2001/XMLSchema-instance" xsi:type="SpreaderPosition">
    <Gantry>2000.730000</Gantry>
    <Hoist>140.000000</Hoist>
    <Trolley>-71.840000</Trolley>
    <SpreaderSize>0</SpreaderSize>
  </DroppedPosition>
</MovementPerformed>
