<?xml version="1.0"?>
<MovementPerformed>
  <GUID>7D018BE7-B41F-4B48-B7A4-523F96865FEB</GUID>
  <LiftedPosition xmlns:xsi="http://www.w3.org/2001/XMLSchema-instance" xsi:type="SpreaderPosition">
    <Gantry>1379.750000</Gantry>
    <Hoist>62.660000</Hoist>
    <Trolley>60.770000</Trolley>
    <SpreaderSize>45</SpreaderSize>
  </LiftedPosition>
  <DroppedPosition xmlns:xsi="http://www.w3.org/2001/XMLSchema-instance" xsi:type="SpreaderPosition">
    <Gantry>1379.750000</Gantry>
    <Hoist>124.020000</Hoist>
    <Trolley>-120.060000</Trolley>
    <SpreaderSize>45</SpreaderSize>
  </DroppedPosition>
</MovementPerformed>
