<?xml version="1.0"?>
<MovementPerformed>
  <GUID>1ACD4D33-6D75-4CB0-9583-AC2B3E0112F7</GUID>
  <LiftedPosition xmlns:xsi="http://www.w3.org/2001/XMLSchema-instance" xsi:type="SpreaderPosition">
    <Gantry>1580.750000</Gantry>
    <Hoist>131.630000</Hoist>
    <Trolley>125.180000</Trolley>
    <SpreaderSize>20</SpreaderSize>
  </LiftedPosition>
  <DroppedPosition xmlns:xsi="http://www.w3.org/2001/XMLSchema-instance" xsi:type="SpreaderPosition">
    <Gantry>1580.740000</Gantry>
    <Hoist>119.610000</Hoist>
    <Trolley>-119.860000</Trolley>
    <SpreaderSize>20</SpreaderSize>
  </DroppedPosition>
</MovementPerformed>
