<?xml version="1.0"?>
<MovementPerformed>
  <GUID>F82948D5-CC1F-4D0A-A9F3-48FFB613CECF</GUID>
  <LiftedPosition xmlns:xsi="http://www.w3.org/2001/XMLSchema-instance" xsi:type="SpreaderPosition">
    <Gantry>1867.030000</Gantry>
    <Hoist>134.740000</Hoist>
    <Trolley>69.750000</Trolley>
    <SpreaderSize>20</SpreaderSize>
  </LiftedPosition>
  <DroppedPosition xmlns:xsi="http://www.w3.org/2001/XMLSchema-instance" xsi:type="SpreaderPosition">
    <Gantry>1867.030000</Gantry>
    <Hoist>133.360000</Hoist>
    <Trolley>-120.920000</Trolley>
    <SpreaderSize>20</SpreaderSize>
  </DroppedPosition>
</MovementPerformed>
