<?xml version="1.0"?>
<MovementPerformed>
  <GUID>F4C3BA11-93DB-4B12-A2B7-FD27A6CED261</GUID>
  <LiftedPosition xmlns:xsi="http://www.w3.org/2001/XMLSchema-instance" xsi:type="SpreaderPosition">
    <Gantry>1867.030000</Gantry>
    <Hoist>148.180000</Hoist>
    <Trolley>69.420000</Trolley>
    <SpreaderSize>20</SpreaderSize>
  </LiftedPosition>
  <DroppedPosition xmlns:xsi="http://www.w3.org/2001/XMLSchema-instance" xsi:type="SpreaderPosition">
    <Gantry>1867.030000</Gantry>
    <Hoist>124.880000</Hoist>
    <Trolley>-120.290000</Trolley>
    <SpreaderSize>20</SpreaderSize>
  </DroppedPosition>
</MovementPerformed>
