<?xml version="1.0"?>
<MovementPerformed>
  <GUID>60B50A74-D856-4E08-81D6-AFD30E82C942</GUID>
  <LiftedPosition xmlns:xsi="http://www.w3.org/2001/XMLSchema-instance" xsi:type="SpreaderPosition">
    <Gantry>1390.170000</Gantry>
    <Hoist>134.130000</Hoist>
    <Trolley>107.930000</Trolley>
    <SpreaderSize>20</SpreaderSize>
  </LiftedPosition>
  <DroppedPosition xmlns:xsi="http://www.w3.org/2001/XMLSchema-instance" xsi:type="SpreaderPosition">
    <Gantry>1390.170000</Gantry>
    <Hoist>136.190000</Hoist>
    <Trolley>-141.120000</Trolley>
    <SpreaderSize>20</SpreaderSize>
  </DroppedPosition>
</MovementPerformed>
