<?xml version="1.0"?>
<MovementPerformed>
  <GUID>3DB51E0D-A6E3-4EFA-A0C4-78493D4B850B</GUID>
  <LiftedPosition xmlns:xsi="http://www.w3.org/2001/XMLSchema-instance" xsi:type="SpreaderPosition">
    <Gantry>1379.710000</Gantry>
    <Hoist>136.550000</Hoist>
    <Trolley>-139.380000</Trolley>
    <SpreaderSize>40</SpreaderSize>
  </LiftedPosition>
  <DroppedPosition xmlns:xsi="http://www.w3.org/2001/XMLSchema-instance" xsi:type="SpreaderPosition">
    <Gantry>1379.710000</Gantry>
    <Hoist>115.240000</Hoist>
    <Trolley>108.460000</Trolley>
    <SpreaderSize>40</SpreaderSize>
  </DroppedPosition>
</MovementPerformed>
