<?xml version="1.0"?>
<MovementPerformed>
  <GUID>B9071653-0C92-4802-90D0-4B6387876115</GUID>
  <LiftedPosition xmlns:xsi="http://www.w3.org/2001/XMLSchema-instance" xsi:type="SpreaderPosition">
    <Gantry>1666.240000</Gantry>
    <Hoist>63.660000</Hoist>
    <Trolley>135.340000</Trolley>
    <SpreaderSize>40</SpreaderSize>
  </LiftedPosition>
  <DroppedPosition xmlns:xsi="http://www.w3.org/2001/XMLSchema-instance" xsi:type="SpreaderPosition">
    <Gantry>1666.240000</Gantry>
    <Hoist>109.040000</Hoist>
    <Trolley>-141.240000</Trolley>
    <SpreaderSize>40</SpreaderSize>
  </DroppedPosition>
</MovementPerformed>
