<?xml version="1.0"?>
<MovementPerformed>
  <GUID>D749C556-8545-4062-B4FD-6CC9DF407ECC</GUID>
  <LiftedPosition xmlns:xsi="http://www.w3.org/2001/XMLSchema-instance" xsi:type="SpreaderPosition">
    <Gantry>2000.430000</Gantry>
    <Hoist>137.050000</Hoist>
    <Trolley>-141.190000</Trolley>
    <SpreaderSize>40</SpreaderSize>
  </LiftedPosition>
  <DroppedPosition xmlns:xsi="http://www.w3.org/2001/XMLSchema-instance" xsi:type="SpreaderPosition">
    <Gantry>2000.430000</Gantry>
    <Hoist>122.050000</Hoist>
    <Trolley>117.690000</Trolley>
    <SpreaderSize>40</SpreaderSize>
  </DroppedPosition>
</MovementPerformed>
