<?xml version="1.0"?>
<MovementPerformed>
  <GUID>6B28E63C-0BA7-44F0-9481-AE372D245EB1</GUID>
  <LiftedPosition xmlns:xsi="http://www.w3.org/2001/XMLSchema-instance" xsi:type="SpreaderPosition">
    <Gantry>1570.830000</Gantry>
    <Hoist>118.680000</Hoist>
    <Trolley>-119.860000</Trolley>
    <SpreaderSize>40</SpreaderSize>
  </LiftedPosition>
  <DroppedPosition xmlns:xsi="http://www.w3.org/2001/XMLSchema-instance" xsi:type="SpreaderPosition">
    <Gantry>1570.840000</Gantry>
    <Hoist>141.470000</Hoist>
    <Trolley>115.920000</Trolley>
    <SpreaderSize>40</SpreaderSize>
  </DroppedPosition>
</MovementPerformed>
