<?xml version="1.0"?>
<MovementPerformed>
  <GUID>E37E265E-0CA1-4C76-B4EC-DF704E1FA9F0</GUID>
  <LiftedPosition xmlns:xsi="http://www.w3.org/2001/XMLSchema-instance" xsi:type="SpreaderPosition">
    <Gantry>2270.320000</Gantry>
    <Hoist>134.470000</Hoist>
    <Trolley>-121.340000</Trolley>
    <SpreaderSize>20</SpreaderSize>
  </LiftedPosition>
  <DroppedPosition xmlns:xsi="http://www.w3.org/2001/XMLSchema-instance" xsi:type="SpreaderPosition">
    <Gantry>2270.320000</Gantry>
    <Hoist>122.240000</Hoist>
    <Trolley>115.730000</Trolley>
    <SpreaderSize>20</SpreaderSize>
  </DroppedPosition>
</MovementPerformed>
