<?xml version="1.0"?>
<MovementPerformed>
  <GUID>A6AF89B5-91F1-4A8E-AC2B-21E4681F4BDC</GUID>
  <LiftedPosition xmlns:xsi="http://www.w3.org/2001/XMLSchema-instance" xsi:type="SpreaderPosition">
    <Gantry>1522.880000</Gantry>
    <Hoist>136.490000</Hoist>
    <Trolley>-140.850000</Trolley>
    <SpreaderSize>40</SpreaderSize>
  </LiftedPosition>
  <DroppedPosition xmlns:xsi="http://www.w3.org/2001/XMLSchema-instance" xsi:type="SpreaderPosition">
    <Gantry>1522.880000</Gantry>
    <Hoist>156.240000</Hoist>
    <Trolley>92.280000</Trolley>
    <SpreaderSize>40</SpreaderSize>
  </DroppedPosition>
</MovementPerformed>
