<?xml version="1.0"?>
<MovementPerformed>
  <GUID>42D335BC-A42C-43A0-ADBF-2D73041DFD97</GUID>
  <LiftedPosition xmlns:xsi="http://www.w3.org/2001/XMLSchema-instance" xsi:type="SpreaderPosition">
    <Gantry>2259.610000</Gantry>
    <Hoist>133.020000</Hoist>
    <Trolley>-121.020000</Trolley>
    <SpreaderSize>40</SpreaderSize>
  </LiftedPosition>
  <DroppedPosition xmlns:xsi="http://www.w3.org/2001/XMLSchema-instance" xsi:type="SpreaderPosition">
    <Gantry>2259.620000</Gantry>
    <Hoist>91.140000</Hoist>
    <Trolley>132.830000</Trolley>
    <SpreaderSize>40</SpreaderSize>
  </DroppedPosition>
</MovementPerformed>
