<?xml version="1.0"?>
<MovementPerformed>
  <GUID>07CB6FEC-1D9A-4E7F-BE5D-757285ABEDAA</GUID>
  <LiftedPosition xmlns:xsi="http://www.w3.org/2001/XMLSchema-instance" xsi:type="SpreaderPosition">
    <Gantry>1523.170000</Gantry>
    <Hoist>138.510000</Hoist>
    <Trolley>-34.010000</Trolley>
    <SpreaderSize>40</SpreaderSize>
  </LiftedPosition>
  <DroppedPosition xmlns:xsi="http://www.w3.org/2001/XMLSchema-instance" xsi:type="SpreaderPosition">
    <Gantry>1522.710000</Gantry>
    <Hoist>81.650000</Hoist>
    <Trolley>137.210000</Trolley>
    <SpreaderSize>40</SpreaderSize>
  </DroppedPosition>
</MovementPerformed>
