<?xml version="1.0"?>
<MovementPerformed>
  <GUID>D8765E21-0EAC-451C-8BD7-E8C8C15706EC</GUID>
  <LiftedPosition xmlns:xsi="http://www.w3.org/2001/XMLSchema-instance" xsi:type="SpreaderPosition">
    <Gantry>1474.840000</Gantry>
    <Hoist>119.090000</Hoist>
    <Trolley>-120.050000</Trolley>
    <SpreaderSize>40</SpreaderSize>
  </LiftedPosition>
  <DroppedPosition xmlns:xsi="http://www.w3.org/2001/XMLSchema-instance" xsi:type="SpreaderPosition">
    <Gantry>1474.850000</Gantry>
    <Hoist>112.980000</Hoist>
    <Trolley>76.090000</Trolley>
    <SpreaderSize>40</SpreaderSize>
  </DroppedPosition>
</MovementPerformed>
