<?xml version="1.0"?>
<MovementPerformed>
  <GUID>63445C87-58C0-4A13-B3FF-219DAFBA4A3F</GUID>
  <LiftedPosition xmlns:xsi="http://www.w3.org/2001/XMLSchema-instance" xsi:type="SpreaderPosition">
    <Gantry>1750.290000</Gantry>
    <Hoist>125.010000</Hoist>
    <Trolley>-119.750000</Trolley>
    <SpreaderSize>20</SpreaderSize>
  </LiftedPosition>
  <DroppedPosition xmlns:xsi="http://www.w3.org/2001/XMLSchema-instance" xsi:type="SpreaderPosition">
    <Gantry>1750.290000</Gantry>
    <Hoist>112.690000</Hoist>
    <Trolley>150.720000</Trolley>
    <SpreaderSize>20</SpreaderSize>
  </DroppedPosition>
</MovementPerformed>
