<?xml version="1.0"?>
<MovementPerformed>
  <GUID>426B177B-247E-420E-B187-15CFF079689D</GUID>
  <LiftedPosition xmlns:xsi="http://www.w3.org/2001/XMLSchema-instance" xsi:type="SpreaderPosition">
    <Gantry>1760.620000</Gantry>
    <Hoist>130.850000</Hoist>
    <Trolley>-26.340000</Trolley>
    <SpreaderSize>20</SpreaderSize>
  </LiftedPosition>
  <DroppedPosition xmlns:xsi="http://www.w3.org/2001/XMLSchema-instance" xsi:type="SpreaderPosition">
    <Gantry>1760.620000</Gantry>
    <Hoist>75.840000</Hoist>
    <Trolley>94.210000</Trolley>
    <SpreaderSize>20</SpreaderSize>
  </DroppedPosition>
</MovementPerformed>
