<?xml version="1.0"?>
<MovementPerformed>
  <GUID>C3008C17-B25E-47C9-BB57-EE42F6DE0282</GUID>
  <LiftedPosition xmlns:xsi="http://www.w3.org/2001/XMLSchema-instance" xsi:type="SpreaderPosition">
    <Gantry>1893.260000</Gantry>
    <Hoist>160.030000</Hoist>
    <Trolley>83.780000</Trolley>
    <SpreaderSize>20</SpreaderSize>
  </LiftedPosition>
  <DroppedPosition xmlns:xsi="http://www.w3.org/2001/XMLSchema-instance" xsi:type="SpreaderPosition">
    <Gantry>1893.260000</Gantry>
    <Hoist>129.080000</Hoist>
    <Trolley>-141.190000</Trolley>
    <SpreaderSize>20</SpreaderSize>
  </DroppedPosition>
</MovementPerformed>
