<?xml version="1.0"?>
<MovementPerformed>
  <GUID>EE7CCBF4-40AA-4B8F-AF27-5B30E6BB52B3</GUID>
  <LiftedPosition xmlns:xsi="http://www.w3.org/2001/XMLSchema-instance" xsi:type="SpreaderPosition">
    <Gantry>1427.060000</Gantry>
    <Hoist>118.050000</Hoist>
    <Trolley>-139.860000</Trolley>
    <SpreaderSize>45</SpreaderSize>
  </LiftedPosition>
  <DroppedPosition xmlns:xsi="http://www.w3.org/2001/XMLSchema-instance" xsi:type="SpreaderPosition">
    <Gantry>1427.060000</Gantry>
    <Hoist>34.010000</Hoist>
    <Trolley>43.820000</Trolley>
    <SpreaderSize>45</SpreaderSize>
  </DroppedPosition>
</MovementPerformed>
