<?xml version="1.0"?>
<MovementPerformed>
  <GUID>35477D1C-E364-462C-9B7C-194B9C6177B2</GUID>
  <LiftedPosition xmlns:xsi="http://www.w3.org/2001/XMLSchema-instance" xsi:type="SpreaderPosition">
    <Gantry>1331.360000</Gantry>
    <Hoist>118.160000</Hoist>
    <Trolley>-119.970000</Trolley>
    <SpreaderSize>45</SpreaderSize>
  </LiftedPosition>
  <DroppedPosition xmlns:xsi="http://www.w3.org/2001/XMLSchema-instance" xsi:type="SpreaderPosition">
    <Gantry>1331.360000</Gantry>
    <Hoist>38.740000</Hoist>
    <Trolley>93.420000</Trolley>
    <SpreaderSize>45</SpreaderSize>
  </DroppedPosition>
</MovementPerformed>
